{
  "quotes": [
    {
      "text": "This is the real secret of life - to be completely engaged with what you are doing in the here and now. And instead of calling it work, realize it is play.",
      "source": "Alan Watts"
    },
    {
      "text": "If you want to change the world, start with the next person who comes to you in need",
      "source": "B. D. Schiers"
    },
    {
      "text": "Awareness is the greatest agent for change.",
      "source": "Eckhart Tolle"
    },
    {
      "text": "Today, you can decide to walk in freedom. You can choose to walk differently. You can walk as a free person, enjoying every step.",
      "source": "Thich Nhat Hanh"
    },
    {
      "text": "No snowflake ever falls in the wrong place",
      "source": "Zen Proverb"
    },
    {
      "text": "When the task is done beforehand, then it is easy",
      "source": "Yuan-tong"
    }
  ]
}
